shaperenderer/__init__.py
shaperenderer/__main__.py
shaperenderer/geometry.py
shaperenderer/renderer.py
shaperenderer/utils.py
shepard_metzler_shape_renderer-2.0.0.dist-info/LICENSE
shepard_metzler_shape_renderer-2.0.0.dist-info/METADATA
shepard_metzler_shape_renderer-2.0.0.dist-info/WHEEL
shepard_metzler_shape_renderer-2.0.0.dist-info/top_level.txt
shepard_metzler_shape_renderer-2.0.0.dist-info/RECORD
