Metadata-Version: 2.1
Name: shepard-metzler-shape-renderer
Version: 2.0.0
Summary: A custom-developed image renderer for generating Shepard & Metzler 3D shapes.
Author-email: Aleksandr Krylov <aleksasha.krylov@gmail.com>
License: The MIT License (MIT)
Project-URL: Homepage, https://github.com/aleksandr-krylov/shepard-metzler-shape-renderer
Keywords: renderer,3D shape,mental rotation
Classifier: License :: OSI Approved :: MIT License
Classifier: Programming Language :: Python
Classifier: Programming Language :: Python :: 3
Requires-Python: >=3.12
License-File: LICENSE
Requires-Dist: numpy>=1.26.4
Requires-Dist: matplotlib>=3.8.4
Provides-Extra: dev
Requires-Dist: black; extra == "dev"
Requires-Dist: bumpver; extra == "dev"
Requires-Dist: isort; extra == "dev"
Requires-Dist: pip-tools; extra == "dev"
Requires-Dist: pytest; extra == "dev"
